imap_tools/__init__.py
imap_tools/consts.py
imap_tools/errors.py
imap_tools/folder.py
imap_tools/idle.py
imap_tools/imap_utf7.py
imap_tools/mailbox.py
imap_tools/message.py
imap_tools/py.typed
imap_tools/query.py
imap_tools/utils.py
imap_tools-1.9.1.dist-info/LICENSE
imap_tools-1.9.1.dist-info/METADATA
imap_tools-1.9.1.dist-info/WHEEL
imap_tools-1.9.1.dist-info/top_level.txt
imap_tools-1.9.1.dist-info/RECORD
