Metadata-Version: 2.2
Name: imap-tools
Version: 1.9.1
Summary: Work with email by IMAP
Home-page: https://github.com/ikvk/imap_tools
Author: Vladimir Kaukin
Author-email: KaukinVK@ya.ru
License: Apache-2.0
Keywords: imap,imap-client,python3,python,email
Classifier: Programming Language :: Python :: 3
Classifier: License :: OSI Approved :: Apache Software License
Classifier: Operating System :: OS Independent
License-File: LICENSE
Dynamic: author
Dynamic: author-email
Dynamic: classifier
Dynamic: description
Dynamic: description-content-type
Dynamic: home-page
Dynamic: keywords
Dynamic: license
Dynamic: summary
